{"status":0,"data":{"cid":"x0B9SeBGFh","authorUid":"bd-526532371","authorUserName":"S***6","title":"圆柱体柱状图","description":"","latestVersion":1,"alwaysLatest":1,"createTime":"2019-05-09T00:35:53.000Z","lastUpdateTime":"2019-05-09T00:35:53.000Z","auth":2,"uid":"bd-526532371","publishedVersion":0,"forkFrom":"-","isSpam":0,"version":1,"parentVersion":-1,"echartsVersion":"4.2.1","versionCreateTime":"2019-05-09T00:35:53.000Z","code":"option = {\r\n            backgroundColor: '#222',\r\n            color: new echarts.graphic.LinearGradient(\r\n                0, 1, 0, 0,\r\n                [\r\n                    { offset: 0, color: '#41a8ff' },\r\n                    { offset: 1, color: '#1070ff' }\r\n                ]\r\n            ),\r\n            grid: {\r\n                top: '30%',\r\n                bottom: '20%',\r\n                left: '10%',\r\n                right: '10%'\r\n            },\r\n            xAxis: {\r\n                data: ['类目1', '类目2', '类目3', '类目4', '类目5'],\r\n                axisTick: {\r\n                    show: false\r\n                },\r\n                axisLine: {\r\n                    lineStyle: {\r\n                        color: '#408eff'\r\n                    }\r\n                },\r\n                axisLabel: {\r\n                    interval: 0,\r\n                    margin: 21,\r\n                    color: '#fff',\r\n                    fontSize: 14,\r\n                    fontFamily: 'Microsoft YaHei',\r\n                    formatter: function (value, index) {\r\n                        if (value.length > 2) {\r\n                            value = value.substring(0, 2) + '\\n' + value.substring(2);\r\n                        }\r\n                        return value;\r\n                    }\r\n                }\r\n            },\r\n            yAxis: {\r\n                splitLine: {\r\n                    show: false\r\n                },\r\n                axisTick: {\r\n                    show: false\r\n                },\r\n                axisLine: {\r\n                    show: false\r\n                },\r\n                axisLabel: {\r\n                    show: false\r\n                }\r\n            },\r\n            series: [{\r\n                type: 'pictorialBar',\r\n                symbolSize: [22, 7],\r\n                symbolOffset: [0, -5],\r\n                z: 12,\r\n                data: [{\r\n                    value: 100,\r\n                    symbolPosition: 'end'\r\n                }, {\r\n                    value: 90,\r\n                    symbolPosition: 'end'\r\n                }, {\r\n                    value: 80,\r\n                    symbolPosition: 'end'\r\n                }, {\r\n                    value: 70,\r\n                    symbolPosition: 'end'\r\n                }, {\r\n                    value: 60,\r\n                    symbolPosition: 'end'\r\n                }]\r\n            }, {\r\n                type: 'pictorialBar',\r\n                symbolSize: [22, 7],\r\n                symbolOffset: [0, 5],\r\n                z: 12,\r\n                itemStyle: {\r\n                    normal: {\r\n                        color: '#41a8ff'\r\n                    }\r\n                },\r\n                data: [100, 90, 80, 70, 60]\r\n            },\r\n            {\r\n                type: 'bar',\r\n                offset: [0, 20],\r\n                label: {\r\n                    show: true,\r\n                    position: 'top',\r\n                    color: '#fff',\r\n                    fontSize: 14,\r\n                    fontFamily: 'Microsoft YaHei',\r\n                    formatter: '{c}%'\r\n                },\r\n                silent: true,\r\n                barWidth: 22,\r\n                data: [100, 90, 80, 70, 60]\r\n            }]\r\n        };","html":"","externalScripts":"","updaterUID":"bd-526532371","theme":"","layout":"","viewCount":698,"userName":"S***6","commentCount":0,"starCount":2,"isStared":0,"thumbnailURL":"https://www.makeapie.com/ecg-storage/ec_gallery_thumbnail/x0B9SeBGFh.png?v=1557362153590","isCustomThumbnail":0,"builtinTags":["category-work","grid","series-bar","series-pictorialBar"],"customTags":[],"updaterUserName":"S***6"}}