{"status":0,"data":{"cid":"x9f0o2s3GS","authorUid":"obd-o-WeIDz9pQFG3HlZjbY3v-MnvKKSvAj","authorUserName":"王***表","title":"饼图--边框","description":"信息产业","latestVersion":1,"alwaysLatest":0,"createTime":"2021-11-12T08:07:12.000Z","lastUpdateTime":"2021-11-12T08:07:12.000Z","auth":2,"uid":"obd-o-WeIDz9pQFG3HlZjbY3v-MnvKKSvAj","publishedVersion":0,"forkFrom":"-","isSpam":0,"version":1,"parentVersion":-1,"echartsVersion":"5.2.2","versionCreateTime":"2021-11-12T08:07:12.000Z","code":"option = {\n    backgroundColor: '#000',\n    color: ['#02f0fe', '#14bcff', '#0054ff', '#ffd684', '#5c30fc', '#2489ff'],\n    title: {\n        text: '32%',\n        subtext: '信息产业',\n        textStyle: {\n            color: '#02f0fe',\n            fontSize: 26,\n            // align: 'center'\n        },\n        subtextStyle: {\n            fontSize: 12,\n            color: ['#fff'],\n        },\n        x: 'center',\n        y: '25%',\n    },\n    grid: {\n        bottom: 150,\n        left: 1,\n        right: '10%',\n    },\n    legend: {\n        icon: 'circle',\n        data: ['信息产业', '科研服务', '金融服务', '交通服务', '农林牧鱼', '文化教育'],\n        bottom: 20,\n        left: 50,\n        textStyle: {\n            color: '#fff',\n        },\n        itemGap: 20,\n    },\n    series: [\n        // 主要展示层的\n        {\n            radius: ['40%', '61%'],\n            center: ['50%', '35%'],\n            type: 'pie',\n            itemStyle: {\n                normal: {\n                    borderWidth: 5,\n                    borderColor: '#1d42a7',\n                },\n            },\n            label: {\n                normal: {\n                    show: false,\n                },\n            },\n            labelLine: {\n                normal: {\n                    show: false,\n                },\n            },\n            name: '民警训练总量',\n            data: [\n                {\n                    name: '信息产业',\n                    value: 10,\n                },\n                {\n                    name: '科研服务',\n                    value: 10,\n                },\n                {\n                    name: '金融服务',\n                    value: 10,\n                },\n                {\n                    name: '交通服务',\n                    value: 10,\n                },\n                {\n                    name: '农林牧鱼',\n                    value: 10,\n                },\n                {\n                    name: '文化教育',\n                    value: 20,\n                },\n            ],\n        },\n    ],\n};\n","html":"","externalScripts":"","updaterUID":"obd-o-WeIDz9pQFG3HlZjbY3v-MnvKKSvAj","theme":"","layout":"","viewCount":0,"userName":"王***表","commentCount":0,"starCount":1,"isStared":0,"thumbnailURL":"https://www.makeapie.com/ecg-storage/ec_gallery_thumbnail/x9f0o2s3GS.png?v=1636704432648","isCustomThumbnail":0,"builtinTags":["category-work","legend","series-pie","title"],"customTags":["pie"],"updaterUserName":"王***表"}}