{"status":0,"data":{"cid":"xB1dUK4uOf","authorUid":"bd-441871429","authorUserName":"牧羊yun","title":"投诉举报受理情况分析_单位立案情况分析","description":"投诉立案数","latestVersion":3,"alwaysLatest":1,"createTime":"2018-03-03T15:03:44.000Z","lastUpdateTime":"2018-03-03T15:03:44.000Z","auth":2,"uid":"bd-441871429","publishedVersion":0,"forkFrom":"-","isSpam":0,"version":3,"parentVersion":2,"echartsVersion":"4.0.4","versionCreateTime":"2018-03-07T03:48:31.000Z","code":"option = {\r\n     backgroundColor:'#fff',\r\n    title : {\r\n        text: '单位立案情况分析',\r\n        subtext: '投诉立案数'\r\n    },\r\n    tooltip : {\r\n        trigger: 'axis'\r\n    },\r\n    legend: {\r\n        data:['投诉立案数']\r\n    },\r\n     grid: {\r\n        left: '3%',\r\n        right: '25%',\r\n        top:'11%',\r\n        bottom: '30%',\r\n        containLabel: true\r\n    },\r\n    color:['#fbceb2','#dbb0e3'],\r\n    toolbox: {\r\n        show : true,\r\n        feature : {\r\n            mark : {show: true},\r\n            dataView : {show: true, readOnly: false},\r\n            magicType : {show: true, type: ['line', 'bar', 'stack', 'tiled']},\r\n            restore : {show: true},\r\n            saveAsImage : {show: true}\r\n        }\r\n    },\r\n    \r\n    calculable : true,\r\n    xAxis : [\r\n        {\r\n            type : 'category',\r\n            boundaryGap : false,\r\n            data: ['南宁市局', '武鸣区局', '横县局', '宾阳县局', '上林县局'\r\n        , '隆安县局','兴宁区分局', '江南区分局', '青秀区分局', '西乡塘区分局', '邕宁区分局',\r\n        '良庆区分局','广西-东盟经济技术开发区行政审批局','广西-东盟经济技术开发区',\r\n        '南宁高新技术产业开发区','南宁经济技术开发区']},\r\n        \r\n    ],\r\n    yAxis : {\r\n            name:'投诉立案数',\r\n            type : 'value'\r\n        }\r\n    ,\"dataZoom\": [{\r\n        \"show\": true,\r\n        \"height\": 30,\r\n        \"xAxisIndex\": [\r\n            0\r\n        ],\r\n        bottom: 30,\r\n        \"start\": 10,\r\n        \"end\": 80,\r\n        handleSize: '110%',\r\n        handleStyle:{\r\n            color:\"#d3dee5\",\r\n            \r\n        },\r\n           textStyle:{\r\n            color:\"#000\"},\r\n           borderColor:\"#90979c\"\r\n        \r\n        \r\n    }, {\r\n        \"type\": \"inside\",\r\n        \"show\": true,\r\n        \"height\": 15,\r\n        \"start\": 1,\r\n        \"end\": 35\r\n    }],\r\n    series : [\r\n        {\r\n            name:'投诉立案数',\r\n            type:'line',\r\n            areaStyle: {\r\n                normal: {type: 'default',\r\n                    color: new echarts.graphic.LinearGradient(0, 0, 0, 1, [{\r\n                        offset: 0,\r\n                        color: 'rgba(199, 37, 50,0.2)'\r\n                    }, {\r\n                        offset: 1,\r\n                        color: 'rgba(199, 37, 50,0.2)'\r\n                    }], false)\r\n                }\r\n            },\r\n            smooth:true,\r\n            itemStyle: {\r\n                normal: {areaStyle: {type: 'default'}}    \r\n            },\r\n            data:[210, 312, 121,654, 500, 830, 710, 521, 304, 560, 330, 410, 710, 521, 304, 560 ]\r\n        }\r\n    ]\r\n};","html":"","externalScripts":"","updaterUID":"bd-441871429","theme":"","layout":"","viewCount":1208,"userName":"牧羊yun","commentCount":0,"starCount":1,"isStared":0,"thumbnailURL":"https://www.makeapie.com/ecg-storage/ec_gallery_thumbnail/xB1dUK4uOf.png?v=1520394511258","isCustomThumbnail":0,"builtinTags":["category-work","dataZoom","grid","legend","series-line","title","toolbox","tooltip"],"customTags":[],"updaterUserName":"牧羊yun"}}