{"status":0,"data":{"cid":"xk9M5AP8Rg","authorUid":"bd-995589324","authorUserName":"155******35","title":"custom map","description":"Data from www.census.gov","latestVersion":2,"alwaysLatest":1,"createTime":"2019-01-16T03:37:13.000Z","lastUpdateTime":"2019-01-16T03:37:13.000Z","auth":2,"uid":"bd-995589324","publishedVersion":0,"forkFrom":"-","isSpam":0,"version":2,"parentVersion":1,"echartsVersion":"4.2.0","versionCreateTime":"2019-01-16T06:31:09.000Z","code":"var uploadedDataURL = \"/asset/get/s/data-1547608545485-yyRMUge-X.json\";\n\nvar uploadedDataURL = \"/asset/get/s/data-1547609362135-8Hiih-zS1.json\";\nvar obj= {\"type\":\"Feature\",\"UTF8Encoding\":false,\"feature\":{\"id\":\"510100\",\"geometry\":{\"type\":\"MultiPolygon\",\"coordinates\":[[\"@@A@BB\",\"@@@CGDF@\",\"@@HBJJJADE@CCMFIBGHGJO@KBAHEPO@EAGLEFG@IEIEAIAKEKIWWCK@W@GDGDCLELSJCDI\\\\KJMAEIEACBIPSAEIKBIJML@LIK@@A@AH@D@@AFBBACC@ECA@EDED@HBDCBBD@DF@BDBFGFFF@DCAEHB@CFAF@BEHEAEDADBFEJIBEDGJ@BBB@DG@CHIBCAAGABECODCD@@EHALGCEAEBADEAABCAA@ABBBAACDEECAIGCBAHAFBJCACIAGE@CLBFC@AC@@CF@CCF@BCFERE@AAAAADA@GNENABGBBBA@MACB@@CXCNI@IACLGBCFAAADCCC@AJABEFAVCABB@BADBC@@DD@BA@ABAA@BAL@J@@EGACC@GDED@BBD@PGZEDG@AJACEF@BFD@DEHCDENKBKEAACHKBMCEAGGGFI@EKAAKACA@G@AC@WCAMAAA@EHAFQPAFJH@HBDCDEDCF@FDNGPFPBBAFC@CAEBAJBDKFCB@DFDBLIDCB@FF\\\\APHFHFBDCBGDAD@JFXAND\\\\GLAJGPCHFJLLBBA@CB@LFBHFADCBADNJFCHDHNVBHJHDADAFEHAFMFADBDLDFBLBDH@HID@\\\\JNDPEFDFALAFBBHFADFD@BDPBDELAFCHAHB@CLGHADEHDPEJDPQXKBCG[@QAEGCGG@GBCL@^ENGlKLGTETDB@FGNIBKFCN@RHH@DEHMJG\\\\CZGTADCBCHCF@FATBHCBA@CEEAEBIPQBELeAEGD@A@IFCJBHFDFHDHABCFYFKBCJGBA@CEKAEJEDCCIDEDALBF@DCB@FBD@BAAE@GBAHDHBNALBJABC@CIIAGBOAKBCBAF@TABADIJGBCBKJOBEFUAMFCF@FLP@JD@ELK@IAIIKIEAIGI@EAAE@AA@EGCGIBCCCBA@EAACBAABAAABAAADAAEDCCCFADBBBFADB@BHFJCDDDA@NJEDBDIBDDBBDHB@CBA@ABCFCDEB@BODEFCBCHCBGAEBCFAFHHDD@HE@C@UCEAGOWBKGACAAIUB[KKHQFOAOAO@IECCBKBI@CA@E@CCCBAAC@EACBAAEBCACDIGA@CCWACD@BJFDDABKBBBDD@BK@BFEDBFQHWFMDBXCDALELEBUFOHWHKFEFAJDXBJNHBBLRBFADG@IFQD@BCDC@@DC@CC@B@BABBBC@A@A@EEAD@B@BC@ABA@C@@EEBACEA@BABBFE@EBEB@DGAADA@EFCCADCCC@@CCAC@@DBDEBABIBAABCAAGB@DCAA@@@BDCBEBKPGFC@OEC@KRAH@BC@MGACAMAEAAEBYJCAAFEE@AFCCCEACDCC@AEBAD@@D@@BI@CB@GBAFAAAIBACCBFE@ACADEICE@E@GKOI@GAAE@KFAA@GACEBMCGDGB]KQ@A@GHUEMJYDGAEAIGAKCGAGBOJOIQAcEC@EDGFEHCHBFCBE@CCGCA_OACDKBECGGECAaHM@AAEICAOBGCOAAB@FHFBDERKXIJIDCCAIBAN@BC@AEIHKCCGAYASPGBCHIBAAAIEE]QUCGACCEEAEBCJG@CUGEEACBAHEFBNDPCBAACSaSUAADG@CGAM@GAKKAEBMAKCAMCACBOAQOOEISSAGDK@GMSGAEIGGEC@CBEEUCGKI@ICICEKIEMGGAGAaCCMKKEGAECEEMAGBEFAJIDODEDGNABCBMCCDBHEDA@GCGBEHENC@GGGBCD@FCDC@]KC@@BCLCBKGEBC@QIO@EBINKJCLMHCHAJDP@FMHENEFSFUTAHMXBHLJ@BI@WFICICCE@CHIBIACICB@CCAKAAODG@UEEB@FCFAHGLEF@PCACICAYCMECA_D_AQ@OFC@SIcSGIDM@CAAC@EDC@MACCASEBICEFCBM@EC@GTW@GAEE@IDE@GGIAGKIMCAI@GBABB@FBEBGACG@@OFA@AA@KJE@IJCACB@CA@CBCDCQIMCmEGAEKAI@AJIAIFK@KACE@QJIDINCDA@EOOWECIACDDFDF@B]DGCI@IIC@GBSGGCCIEA_ISEDKNSB@BCCEQU[KIECOACAAGDEAMMMQIQCAA@APCHCDGFABDLALICE@GHM@E@CC@CFKDCNELIDK@CCICEGEEAG@IBCDAFIPAFFHAD@DHBDDCDGFAAMCBGFACE@IACECE@A@GNE@EEICW[ECG@EBGFANQHCHIJBHEHADEHIBCD@FPHFNENFPCFQFCD@FBDFFDF@DGJ@HJFHJALHHBH@JCTKBEFOBMHGCKD[IGBADDTCNGNCDWFM@OAOBu[UMGQESEGBGAEEGMEGBEDCHBNCJCNEFCFEDC@IGABUVCBGCGOOQUcEEMEW@GACDEFIDP@DDJ@FAHKNBNA\\\\MBCDAFAFDNLdMP@HDHDDLDNVD@DCFBLFVVv|@HCHEDKDADDJFTADEJBREFJJDNGP@BDLDBD@LGJAH@DH@BADQHIHADBDJFPRFJJFRFDCBEH@@D@BFHBHFDBHLNDNJJFF@DGPCB@DBDUAKBKDAFNbDTCLEFMLEHAP@DEBUEMHCHCH@FBD@VBFJNDJCXBVAJCFKLCNIHS@KDIFEHGV[TAFDREFCBI@yYIAE@AB@FDZ@BGLSTOHMNOZELAJ@JAHHBHBFDFH@FFDPBjT`@DBPLPJN@LATKNEZMNEBAFAJFLNHXDFJBJHNJR`LFHDH@JCTDJATMHAHALBPCJBNDNAHDFDF@LQBAHCLCLBH@JIFIDMPEF@`RRNPAHPHNTXPBLFTJJF`@VD`^D@LANJHBPPDLDLAjDNRV\\\\Rp\\\\FLDBRBD@BF@@EFAPDPFHBJ@NETAVEHQHAFJRHLHFFLBHAXHJHHBDEL@JHFDPFBPVFNDPJNFDDDBDAFJNF^HBLHPRBDAdKPHdBR@JOVIHBZR\\\\BFING\\\\@HBJCNAHBNDDDBNA^DJFHLB@HAHGR@LCBBJJHBTDVEVHHHDHJJFJTNLLDDBJJBT@NFP@HDLDFHDN@JLJTHTFJFVJF@HEN@DAFBFHD@HAFCDSVSDANFNCRBPHLHD@JIFCF@\"]],\"encodeOffsets\":[[[106606,31777],[105927,30843],[106375,32170]]]},\"properties\":{\"cp\":[104.065735,30.659462],\"name\":\"成都\",\"childNum\":3}}}\n\nmyChart.showLoading();\n\n$.getJSON(uploadedDataURL, function (usaJson) {\n    myChart.hideLoading();\n    echarts.registerMap('Custom', obj);\n    option = {\n        \n        tooltip: {\n            trigger: 'item',\n            showDelay: 0,\n            transitionDuration: 0.2,\n            formatter: function (params) {\n                var value = (params.value + '').split('.');\n                value = value[0].replace(/(\\d{1,3})(?=(?:\\d{3})+(?!\\d))/g, '$1,');\n                return params.seriesName + '<br/>' + params.name + ': ' + value;\n            }\n        },\n        visualMap: {\n            left: 'right',\n            min: 500000,\n            max: 38000000,\n            color: ['orangered','yellow','lightskyblue'],\n            text:['High','Low'],           // 文本，默认为数值文本\n            calculable: true\n        },\n        toolbox: {\n            show: true,\n            //orient: 'vertical',\n            left: 'left',\n            top: 'top',\n            feature: {\n                dataView: {readOnly: false},\n                restore: {},\n                saveAsImage: {}\n            }\n        },\n        series: [\n            {\n                name: 'Custom map',\n                type: 'map',\n                roam: true,\n                map: 'Custom',\n                itemStyle:{\n                    emphasis:{label:{show:true}}\n                },\n                // 文本位置修正\n                textFixed: {\n                    Alaska: [20, -20]\n                },\n                data:[\n                   \n                ]\n            }\n        ]\n    };\n\n    myChart.setOption(option);\n});","html":"","externalScripts":"","updaterUID":"bd-995589324","theme":"","layout":"","viewCount":72,"userName":"155******35","commentCount":0,"starCount":0,"isStared":0,"thumbnailURL":"https://www.makeapie.com/ecg-storage/ec_gallery_thumbnail/xk9M5AP8Rg.png?v=1547620269688","isCustomThumbnail":0,"builtinTags":["category-work","toolbox","tooltip"],"customTags":[],"updaterUserName":"155******35"}}