{"status":0,"data":{"cid":"xlP3fBVMvB","authorUid":"obd-oDoZIY2Utcmo-T-oDy9pwF--e8gVz15","authorUserName":"q***6","title":"","description":"","latestVersion":1,"alwaysLatest":0,"createTime":"2021-12-23T09:23:15.000Z","lastUpdateTime":"2021-12-23T09:23:15.000Z","auth":2,"uid":"obd-oDoZIY2Utcmo-T-oDy9pwF--e8gVz15","publishedVersion":0,"forkFrom":"-","isSpam":0,"version":1,"parentVersion":-1,"echartsVersion":"5.2.2","versionCreateTime":"2021-12-23T09:23:15.000Z","code":"var data = [220, 182, 191, 234, 290, 120, 180, 240, 300, 100];\nvar sum = eval(data.join('+'));\nvar colors = [\n    {\n        type: 'linear',\n        x: 0,\n        x2: 0,\n        y: 1,\n        y2: 0,\n        colorStops: [\n            {\n                offset: 0,\n                color: '#007fd4',\n            },\n            {\n                offset: 0.5,\n                color: '#3ffcc2',\n            },\n            {\n                offset: 0.5,\n                color: '#fff726',\n            },\n            {\n                offset: 1,\n                color: '#fff726',\n            },\n        ],\n    },\n];\n\nvar barWidth = 20;\n\noption = {\n    backgroundColor: '#0B1837',\n    textStyle: {\n        color: '#fff',\n        fontSize: 14,\n    },\n    grid: {\n        left: '12%',\n        top: '2%',\n        right: '10%',\n        bottom: '2%',\n    },\n    tooltip: {\n        trigger: 'axis',\n        axisPointer: {\n            // 坐标轴指示器，坐标轴触发有效\n            type: 'shadow', // 默认为直线，可选为：'line' | 'shadow'\n        },\n        formatter: function (params) {\n            // let obj = params.data.info\n            // console.log(params);\n\n            let titleName = params[0].axisValue;\n            let list = [];\n            let listItem = '';\n\n            for (var i = 0; i < params.length; i++) {\n                if (params[i].seriesName !== '') {\n                    list.push(params[i].seriesName + '：' + params[i].value);\n                }\n            }\n\n            listItem = list.join('<br>');\n\n            return '<span style=\"font-size: 16px;\">' + titleName + '</span>' + '<br />' + listItem;\n        },\n    },\n    yAxis: {\n        inverse: true,\n        offset: 3,\n        axisLine: {\n            show: 0,\n        },\n        axisTick: {\n            show: 0,\n        },\n        axisLabel: {\n            fontSize: 14,\n        },\n        data: [\n            '浙江省档案馆',\n            '杭州市档案馆',\n            '宁波市档案馆',\n            '温州市档案馆',\n            '嘉兴市档案馆',\n            '湖州市档案馆',\n            '绍兴市档案馆',\n            '金华市档案馆',\n            '衢州市档案馆',\n            '舟山市档案馆',\n        ],\n    },\n    xAxis: {\n        axisLabel: {\n            show: 0,\n        },\n        axisLine: {\n            show: 0,\n        },\n        axisTick: {\n            show: 0,\n        },\n        splitLine: {\n            show: 0,\n        },\n    },\n    series: [\n        {\n            z: 1,\n            name: '',\n            type: 'bar',\n            barWidth: barWidth,\n            // symbolSize: 0,\n            // showSymbol: false, // 不显示\n            data: data,\n            itemStyle: {\n                normal: {\n                    color: colors[0],\n                },\n            },\n        },\n        {\n            z: 2,\n            name: '去年',\n            type: 'pictorialBar',\n            // data: [0, 0, 0, 0, 0, 0, 0, 0, 0, 0],\n            data: [120, 80, 240, 300, 100, 60, 90, 120, 150, 50],\n            symbol: 'diamond',\n            symbolOffset: ['-50%', 0],\n            symbolSize: [10, barWidth],\n            // symbolSize: [10, barWidth],\n            itemStyle: {\n                normal: {\n                    color: colors[0],\n                },\n            },\n        },\n        {\n            z: 3,\n            name: '今年',\n            type: 'pictorialBar',\n            symbolPosition: 'end',\n            data: data,\n            symbol: 'diamond',\n            symbolOffset: ['50%', 0],\n            symbolSize: [(10 * (barWidth - 4)) / barWidth, barWidth - 4],\n            itemStyle: {\n                normal: {\n                    borderColor: '#0f9cd0',\n                    borderWidth: 2,\n                    color: '#0f9cd0',\n                },\n            },\n            label: {\n                show: true,\n                position: 'right',\n                offset: [10, 0],\n                formatter: (p) => {\n                    return ((p.value / sum) * 100).toFixed() + '%';\n                },\n                fontSize: 14,\n                color: '#fff',\n            },\n        },\n    ],\n};\n","html":"","externalScripts":"","updaterUID":"obd-oDoZIY2Utcmo-T-oDy9pwF--e8gVz15","theme":"","layout":"","viewCount":0,"userName":"q***6","commentCount":0,"starCount":0,"isStared":0,"thumbnailURL":"https://www.makeapie.com/ecg-storage/ec_gallery_thumbnail/xlP3fBVMvB.png?v=1640251395816","isCustomThumbnail":0,"builtinTags":["category-work","grid","series-bar","series-pictorialBar","tooltip"],"customTags":[],"updaterUserName":"q***6"}}