{"status":0,"data":{"cid":"xMf8Zjd4B-","authorUid":"bd-365218436","authorUserName":"G***G","title":"横向柱状图","description":"","latestVersion":2,"alwaysLatest":1,"createTime":"2021-02-23T01:56:29.000Z","lastUpdateTime":"2021-02-23T01:56:29.000Z","auth":2,"uid":"bd-365218436","publishedVersion":0,"forkFrom":"-","isSpam":0,"version":2,"parentVersion":1,"echartsVersion":"4.8.0","versionCreateTime":"2021-02-23T02:04:01.000Z","code":"\r\nlet yLabel = ['幼儿园', '小一', '小二', '小三','小四','小五','小六','初一','初二','初三','高一','高二','高三']\r\nlet yData = [653, 755,705,655,675,654,802,769,513,755,755,1051,726]\r\nlet bgData = []\r\nfor(let i in yData){\r\n    bgData.push(2000)\r\n}\r\noption = {\r\n    grid: {\r\n        left: '5%',\r\n        right: '5%',\r\n        bottom: '5%',\r\n        top: '10%',\r\n        containLabel: true\r\n    },\r\n    tooltip: {\r\n        trigger: 'axis',\r\n        axisPointer: {\r\n            type: 'none'\r\n        },\r\n        formatter: function(params) {\r\n            return params[0].name + '<br/>' +\r\n                \"<span style='display:inline-block;margin-right:5px;border-radius:10px;width:9px;height:9px;background-color:rgba(36,207,233,0.9)'></span>\" +\r\n                params[0].seriesName + ' : ' + params[0].value + ' <br/>'\r\n        }\r\n    },\r\n    backgroundColor: 'rgb(20,28,52)',\r\n    xAxis: {\r\n        show: false,\r\n        type: 'value'\r\n    },\r\n    yAxis: [{\r\n        type: 'category',\r\n        inverse: true,\r\n        axisLabel: {\r\n            show: true,\r\n            margin:15,\r\n            textStyle: {\r\n                color: '#fff',\r\n            },\r\n        },\r\n        splitLine: {\r\n            show: false\r\n        },\r\n        axisTick: {\r\n            show: false\r\n        },\r\n        axisLine: {\r\n            show: false\r\n        },\r\n        data: yLabel\r\n    }, {\r\n        type: 'category',\r\n        inverse: true,\r\n        axisTick: 'none',\r\n        axisLine: 'none',\r\n        show: true,\r\n        axisLabel: {\r\n            textStyle: {\r\n                color: '#9aeced',\r\n                fontSize: '12'\r\n            },\r\n        },\r\n        data: yData\r\n    }],\r\n    series: [{\r\n            name: '人数',\r\n            type: 'bar',\r\n            zlevel: 1,\r\n            itemStyle: {\r\n                normal: {\r\n                    barBorderRadius: [0,30,30,0],\r\n                    color: new echarts.graphic.LinearGradient(0, 0, 1, 0, [{\r\n                        offset: 0,\r\n                        color: '#52d8da'\r\n                    }, {\r\n                        offset: 1,\r\n                        color: '#57dcde'\r\n                    }]),\r\n                    shadowBlur:0,\r\n                    shadowColor:'rgba(87,220,222,0.7)'\r\n                },\r\n            },\r\n            barWidth: 20,\r\n            data: yData\r\n        },\r\n        {\r\n            name: '背景',\r\n            type: 'bar',\r\n            barWidth: 20,\r\n            barGap: '-100%',\r\n            data: bgData,\r\n            itemStyle: {\r\n                normal: {\r\n                    color: 'rgba(24,31,68,1)',\r\n                    barBorderRadius: [0,30,30,0],\r\n                }\r\n            },\r\n        },\r\n    ]\r\n};","html":"","externalScripts":"","updaterUID":"bd-365218436","theme":"","layout":"","viewCount":117,"userName":"G***G","commentCount":0,"starCount":40,"isStared":0,"thumbnailURL":"https://www.makeapie.com/ecg-storage/ec_gallery_thumbnail/xMf8Zjd4B-.png?v=1614045841585","isCustomThumbnail":0,"builtinTags":["category-work","grid","series-bar","tooltip"],"customTags":[],"updaterUserName":"G***G"}}