{"status":0,"data":{"cid":"xSk6twsXYG","authorUid":"bd-1679792466","authorUserName":"沉沦在回忆中","title":"受理案件数量趋势分析","description":"","latestVersion":5,"alwaysLatest":1,"createTime":"2018-03-12T07:08:52.000Z","lastUpdateTime":"2018-03-12T07:08:52.000Z","auth":2,"uid":"bd-1679792466","publishedVersion":0,"forkFrom":"-","isSpam":0,"version":5,"parentVersion":4,"echartsVersion":"4.0.4","versionCreateTime":"2018-03-13T09:38:13.000Z","code":"option = {\r\n    title : {\r\n       text: '受理案件数量趋势分析',\r\n    },\r\n    backgroundColor:'#fff',\r\n    tooltip : {\r\n        trigger: 'axis'\r\n    },\r\n     grid: {\r\n        left: '15%',\r\n        top:'15%',\r\n        bottom:'50%',\r\n        right:'20%',\r\n        containLabel: true\r\n    },\r\n    color:['#FF8C00','#7fdfd0','#54FF9F','#BF3EFF'],\r\n   legend: {\r\n       top:50,\r\n        data:['一般程序案件数','简易程序案件数','办结案件数','移送司法机关数']\r\n    },\r\n    calculable : true,\r\n    xAxis : [\r\n        {\r\n            type : 'category',\r\n            boundaryGap : false,\r\n            data : ['1月','2月','3月','4月','5月','6月','7月','8月','9月','10月','11月','12月']\r\n        }\r\n    ],\r\n    yAxis : {\r\n            type : 'value'\r\n        }\r\n    ,\r\n    series : [\r\n        {\r\n            name:'一般程序案件数',\r\n            type:'line',\r\n            areaStyle: {\r\n                normal: {type: 'default',\r\n                    color:'#b4e6f2'\r\n                }\r\n            },\r\n            smooth:true,\r\n            itemStyle: {\r\n                normal: {areaStyle: {type: 'default'}}    \r\n            },\r\n            data:[639,602,657,656,792,821,903,644,646,842,819,715]\r\n        },\r\n         {\r\n            name:'简易程序案件数',\r\n            type:'line',\r\n            areaStyle: {\r\n                normal: {type: 'default',\r\n                    color: '#b4eee5'\r\n                }\r\n            },\r\n            smooth:true,\r\n            itemStyle: {normal: {areaStyle: {type: 'default'}}},\r\n            data:[768,563,889,686,821,823,641,852,657,801,725,731]\r\n        },\r\n         {\r\n            name:'办结案件数',\r\n            type:'line',\r\n            areaStyle: {\r\n                normal: {type: 'default',\r\n                    color: '#93d2e4'\r\n                }\r\n            },\r\n            smooth:true,\r\n            itemStyle: {normal: {areaStyle: {type: 'default'}}},\r\n            data:[353,311,312,345,399,232,233,237,284,211,356,318]\r\n        },\r\n         {\r\n            name:'移送司法机关数',\r\n            type:'line',\r\n            areaStyle: {\r\n                normal: {type: 'default',\r\n                    color:'#7fa9c3'\r\n                }\r\n            },\r\n            smooth:true,\r\n            itemStyle: {normal: {areaStyle: {type: 'default'}}},\r\n            data:[283,217,234,406,325,372,229,291,273,358,325,214]\r\n        }\r\n    ]\r\n};","html":"","externalScripts":"","updaterUID":"bd-1679792466","theme":"","layout":"","viewCount":90,"userName":"沉沦在回忆中","commentCount":0,"starCount":2,"isStared":0,"thumbnailURL":"https://www.makeapie.com/ecg-storage/ec_gallery_thumbnail/xSk6twsXYG.png?v=1520933893782","isCustomThumbnail":0,"builtinTags":["category-work","grid","legend","series-line","title","tooltip"],"customTags":[],"updaterUserName":"沉沦在回忆中"}}