{"status":0,"data":{"cid":"xSyFnchsWZ","authorUid":"bd-1226551401","authorUserName":"陈拉拉1209","title":"年度每月设备数量一览","description":"数据都为正数的需求图","latestVersion":1,"alwaysLatest":1,"createTime":"2017-05-31T03:38:25.000Z","lastUpdateTime":"2017-05-31T03:38:25.000Z","auth":2,"uid":"bd-1226551401","publishedVersion":0,"forkFrom":"-","isSpam":0,"version":1,"parentVersion":-1,"echartsVersion":"3.6.1","versionCreateTime":"2017-05-31T03:38:25.000Z","code":"option = {\n    color:[\"#69d2e7\",\"#4cafff\",\"#ef553b\"],\n    toolbox: {\n        show : true,\n        feature : {\n            mark : {show: true},\n            dataView : {show: true, readOnly: false},\n            magicType : {show: true, type: ['line', 'bar', 'stack', 'tiled']},\n            restore : {show: true},\n            saveAsImage : {show: true}\n        }\n    },\n    title: {\n        text: '年度每月设备数量一览',\n        x: 'center'\n    },\n    tooltip: {\n        trigger: 'axis',\n        /*formatter: function (params) {\n            if(params.length<2){\n            return params[0].name + '<br/>'\n                + params[0].seriesName + ' : ' + params[0].value + ' <br/>';\n            }else{\n                 return params[0].name + '<br/>'\n                + params[0].seriesName + ' : ' + params[0].value + ' <br/>'\n                + params[1].seriesName + ' : ' + params[1].value + ' <br/>';\n            }\n        },*/\n        axisPointer: {\n            animation: false\n        }\n    },\n    legend: {\n        data:['在线','接入','离线'],\n        bottom: '1',\n        itemHeight:'10'\n    },\n\n    grid: [{\n       top:'13%', \n       left:'4%',\n        height: '35%',\n        width:'92%'\n    }, {\n        \n        left:'4%',\n        top: '52%',\n        height: '35%',\n        width:'92%'\n    }],\n    xAxis : [\n        {\n            type : 'category',\n            boundaryGap : true,\n            scale: true,\n            nameTextStyle:{\n            \tfontSize:'10'\n            },\n            axisTick:{\n\t\t        \tshow:false\n\t\t        },\n            axisLine: {show:false,onZero: true},\n            axisLabel:{interval:'0'},\n\t        nameLocation:'start',\n            data:  ['一月','二月','三月','四月','五月','六月','七月','八月','九月','十月','十一月','十二月']\n        },\n        { \n        \tshow:false,\n            gridIndex: 1,\n            type : 'category',\n            scale: true,\n             axisTick:{\n\t\t        \tshow:false\n\t\t        },\n\t\t    axisLabel:{interval:'0'},\n\t        boundaryGap : true,\n            axisLine: {onZero: true,\n            \tshow:false\n            },\n            data:  ['一月','二月','三月','四月','五月','六月','七月','八月','九月','十月','十一月','十二月'],\n            position: 'top'\n        }\n    ],\n    yAxis : [\n        {\n            show:false,\n            name : '多头',\n            type : 'value',\n            \n        },\n        {\n            show:false,\n            gridIndex: 1,\n            name : '空头',\n            type : 'value',\n             max:300,\n            inverse: true\n        }\n    ],\n    series : [\n        {\n            name:'在线',\n            type:'bar',\n            barWidth: '99.3%',\n            symbolSize: 1,\n            stack: '广告',\n            hoverAnimation: false,\n            data: [320, 302, 301, 334, 390, 330, 320,120, 132, 101, 134,210]\n        },\n        {\n            name:'接入',\n            type:'bar',\n            stack: '广告',\n            barWidth: '99.3%',\n            symbolSize: 1,\n            hoverAnimation: false,\n           data: [220, 182, 191, 234, 290, 330, 310, 230, 210,145,250,170]\n        },\n        {\n            name:'离线',\n            type:'bar',\n            barWidth: '99.3%',\n            xAxisIndex: 1,\n            yAxisIndex: 1,\n            symbolSize: 8,\n            hoverAnimation: false,\n            data: [100,90,120,70,50,110,90,100,90,120,70,50]\n        }\n    ]\n};","html":"","externalScripts":"","updaterUID":"bd-1226551401","theme":"","layout":"","viewCount":303,"userName":"陈拉拉1209","commentCount":0,"starCount":0,"isStared":0,"thumbnailURL":"https://www.makeapie.com/ecg-storage/ec_gallery_thumbnail/xSyFnchsWZ.png?v=1496201905608","isCustomThumbnail":0,"builtinTags":["category-work","grid","legend","series-bar","title","toolbox","tooltip"],"customTags":[],"updaterUserName":"陈拉拉1209"}}