{"status":0,"data":{"cid":"xzkzaOAlh","authorUid":"bd-3308202265","authorUserName":"L***灾","title":"等分仪表盘 ","description":"饼图 模仿仪表盘 ","latestVersion":1,"alwaysLatest":1,"createTime":"2020-01-13T11:00:24.000Z","lastUpdateTime":"2020-01-13T11:00:24.000Z","auth":2,"uid":"bd-3308202265","publishedVersion":0,"forkFrom":"-","isSpam":0,"version":1,"parentVersion":-1,"echartsVersion":"4.4.0","versionCreateTime":"2020-01-13T11:00:24.000Z","code":"var a = 0;\n\noption = {\n    tooltip: {\n        trigger: 'item',\n        formatter: '{a} <br/>{b}: {c} ({d}%)'\n    },\n    backgroundColor:'#fff',\n    legend: {\n        orient: 'vertical',\n        left: 10,\n        data: ['直达'],\n        borderWidth:\"10\",\n        borderColor:\"#f00\"\n    },\n    series: [\n        {\n            name: '访问来源',\n            type: 'pie',\n            \n            radius: [0, '30%'],\n            label: {\n                show:true,\n                position:\"inner\"\n            },\n            labelLine: {\n                show: false\n            },\n            data: [\n                {value: 1548, name: '搜索引擎'}\n            ]\n        },\n        {\n            name: '访问来源',\n            type: 'pie',\n            radius: ['40%', '55%'],\n            label:{\n                 padding: [80, -10,50,-10],\n                formatter: [\n                    '{a| 12}'\n                ].join('\\n'),\n                rich: {\n                    a: {\n                    \n                        top: 10,\n                        right: 100\n                    },\n                    b: {\n                        backgroundColor: {\n                            image: 'xxx/xxx.jpg'\n                        },\n                        height: 40\n                    }\n    }\n            },\n            labelLine:{\n                    show:false\n            },\n            startAngle:242,\n            hoverAnimation:false,\n            data: [\n                {value: 100, name: 'aaa'},\n                {value: 100, name: 'bbb'},\n                {value: 100, name: 'ccc'},\n                \n                {value: 100, name: 'ccc'},\n                {value: 100, name: 'ccc'},\n                {value: 100, name: 'ccc'},\n                {value: 100, name: 'ddd',itemStyle:{normal:{color:'rgba(255,0,0,0.5)'}}},\n                {value: 100, name: 'eee',itemStyle:{normal:{color:'rgba(255,0,0,0.5)'}}},\n                {value: 150, name: 'fff',itemStyle:{normal:{color:'rgba(0,0,0,0)'}}}\n            ],\n            itemStyle:{\n                normal:{\n                    borderColor:\"#fff\",\n                    borderWidth:\"5\",\n                    color:\"#ccc\"\n                }\n            },\n        }\n    ]\n};","html":"","externalScripts":"","updaterUID":"bd-3308202265","theme":"","layout":"","viewCount":79,"userName":"L***灾","commentCount":0,"starCount":0,"isStared":0,"thumbnailURL":"https://www.makeapie.com/ecg-storage/ec_gallery_thumbnail/xzkzaOAlh.png?v=1578913224696","isCustomThumbnail":0,"builtinTags":["category-work","legend","series-pie","tooltip"],"customTags":[],"updaterUserName":"L***灾"}}